{
  "log_info": {
    "filepath": "../test_tables/state.csv",
    "table_name": "",
    "src_format": "csv"
  },
  "uuid": "c9271151-4feb-4bf2-8b59-084a39edda02",
  "timestamp": "2025-09-04T03:39:45.245303+00:00",
  "executed_user": "Daniel Stamer-Squair",
  "event_type": "load",
  "event_description": "Loaded  from ../test_tables/state.csv",
  "meta_version": "1.0",
  "class_type": "PipelineEvent"
}
{
  "log_info": {
    "filepath": "..\\test_tables\\output\\state.parquet",
    "table_name": {},
    "out_format": "parquet"
  },
  "uuid": "d5aaa002-9a4e-4cfd-8f1f-53714462d96f",
  "timestamp": "2025-09-04T03:39:57.543576+00:00",
  "executed_user": "Daniel Stamer-Squair",
  "event_type": "write",
  "event_description": "Wrote table to ..\\test_tables\\output\\state.parquet as parquet (pyspark)",
  "meta_version": "1.0",
  "filepath": "..\\test_tables\\output\\state.parquet",
  "table_name": {},
  "src_format": "parquet",
  "class_type": "PipelineEvent"
}
