{
  "log_info": {
    "filepath": "../test_tables/job_1/state.csv",
    "table_name": "",
    "src_format": "csv"
  },
  "uuid": "f3fa841b-91cc-40e7-a8f8-7f62e5176af8",
  "timestamp": "2025-09-08T15:19:16.320605+00:00",
  "executed_user": "Daniel Stamer-Squair",
  "event_type": "load",
  "event_description": "Loaded  from ../test_tables/job_1/state.csv",
  "meta_version": "1.0",
  "class_type": "PipelineEvent"
}
{
  "log_info": {
    "filepath": "..\\test_tables\\output\\state.parquet",
    "table_name": {},
    "out_format": "parquet"
  },
  "uuid": "585488d5-1b64-4c80-9126-ada8d7844eea",
  "timestamp": "2025-09-08T15:19:29.268480+00:00",
  "executed_user": "Daniel Stamer-Squair",
  "event_type": "write",
  "event_description": "Wrote table to ..\\test_tables\\output\\state.parquet as parquet (pyspark)",
  "meta_version": "1.0",
  "filepath": "..\\test_tables\\output\\state.parquet",
  "table_name": {},
  "src_format": "parquet",
  "class_type": "PipelineEvent"
}
