{
  "log_info": {
    "filepath": "../test_tables/location.csv",
    "table_name": "",
    "src_format": "csv"
  },
  "uuid": "a1d6a868-7c3c-4194-a719-0b3a56c02068",
  "timestamp": "2025-09-04T03:49:01.741971+00:00",
  "executed_user": "Daniel Stamer-Squair",
  "event_type": "load",
  "event_description": "Loaded  from ../test_tables/location.csv",
  "meta_version": "1.0",
  "class_type": "PipelineEvent"
}
{
  "log_info": {
    "input_tables": [
      "location",
      "state"
    ],
    "output_tables": [
      "location"
    ],
    "input_variables": [
      [
        "CITY"
      ]
    ],
    "output_variables": [],
    "created_variables": null,
    "renamed_variables": null,
    "removed_variables": null,
    "num_input_frames": 2,
    "num_output_frames": 1
  },
  "uuid": "fa18c9b0-f9be-412a-a109-f7029e8b65a7",
  "timestamp": "2025-09-04T03:49:09.878219+00:00",
  "executed_user": "Daniel Stamer-Squair",
  "event_type": "transform",
  "event_description": "Joins location and state on CITY (outer)",
  "meta_version": "1.0",
  "name": "JoinTable",
  "transform_type": "TableTransform",
  "testable_transform": true,
  "version_pyspark": "4.0.0",
  "version_polars": "1.31.0",
  "version_pandas": "2.3.0",
  "version_python": "3.11.9",
  "params": {
    "output_table": "location"
  },
  "transform_id": "JoinTbl",
  "target_tables": [
    "location"
  ],
  "target_variables": [
    "CITY"
  ],
  "left_table": "location",
  "right_table": "state",
  "join_columns": [
    "CITY"
  ],
  "join_type": "outer",
  "suffixes": [
    "_left",
    "_right"
  ],
  "class_type": "JoinTable"
}
{
  "log_info": {
    "input_tables": [
      "location"
    ],
    "output_tables": [
      "location"
    ],
    "input_variables": [],
    "output_variables": [],
    "created_variables": null,
    "renamed_variables": null,
    "removed_variables": null,
    "num_input_frames": 1,
    "num_output_frames": 1
  },
  "uuid": "12b5b3bf-58c6-45cd-9063-757d7726e18a",
  "timestamp": "2025-09-04T03:49:10.034342+00:00",
  "executed_user": "Daniel Stamer-Squair",
  "event_type": "transform",
  "event_description": "Removes duplicate rows from a DataFrame",
  "meta_version": "1.0",
  "name": "DistinctTable",
  "transform_type": "TableTransform",
  "testable_transform": false,
  "version_pyspark": "4.0.0",
  "version_polars": "1.31.0",
  "version_pandas": "2.3.0",
  "version_python": "3.11.9",
  "params": {
    "df": "location"
  },
  "transform_id": "DistinctTbl",
  "target_tables": [
    "location"
  ],
  "target_variables": [],
  "class_type": "DistinctTable"
}
{
  "log_info": {
    "input_tables": [
      "location",
      "example_join"
    ],
    "output_tables": [
      "final"
    ],
    "input_variables": [
      [
        "NAME"
      ]
    ],
    "output_variables": [],
    "created_variables": null,
    "renamed_variables": null,
    "removed_variables": null,
    "num_input_frames": 2,
    "num_output_frames": 1
  },
  "uuid": "6a245248-e827-402f-8d44-5c3a84086ca5",
  "timestamp": "2025-09-04T03:49:10.532864+00:00",
  "executed_user": "Daniel Stamer-Squair",
  "event_type": "transform",
  "event_description": "Joins location and example_join on NAME (outer)",
  "meta_version": "1.0",
  "name": "JoinTable",
  "transform_type": "TableTransform",
  "testable_transform": true,
  "version_pyspark": "4.0.0",
  "version_polars": "1.31.0",
  "version_pandas": "2.3.0",
  "version_python": "3.11.9",
  "params": {
    "output_table": "final"
  },
  "transform_id": "JoinTbl",
  "target_tables": [
    "final"
  ],
  "target_variables": [
    "NAME"
  ],
  "left_table": "location",
  "right_table": "example_join",
  "join_columns": [
    "NAME"
  ],
  "join_type": "outer",
  "suffixes": [
    "_left",
    "_right"
  ],
  "class_type": "JoinTable"
}
{
  "log_info": {
    "filepath": "..\\test_tables\\output\\final.parquet",
    "table_name": {},
    "out_format": "parquet"
  },
  "uuid": "cbf8030a-bf24-4d55-ac6d-3e006d6e782e",
  "timestamp": "2025-09-04T03:49:15.993745+00:00",
  "executed_user": "Daniel Stamer-Squair",
  "event_type": "write",
  "event_description": "Wrote table to ..\\test_tables\\output\\final.parquet as parquet (pyspark)",
  "meta_version": "1.0",
  "filepath": "..\\test_tables\\output\\final.parquet",
  "table_name": {},
  "src_format": "parquet",
  "class_type": "PipelineEvent"
}
